quantumsim/__init__.py
quantumsim/circuit.py
quantumsim/dm10.py
quantumsim/dm_np.py
quantumsim/photons.py
quantumsim/primitives.cu
quantumsim/ptm.py
quantumsim/sparsedm.py
quantumsim/tp.py
quantumsim/qasm/__init__.py
quantumsim/qasm/configurable.py
quantumsim/qasm/universal.py
quantumsim-0.2.0.dist-info/LICENSE
quantumsim-0.2.0.dist-info/METADATA
quantumsim-0.2.0.dist-info/WHEEL
quantumsim-0.2.0.dist-info/top_level.txt
quantumsim-0.2.0.dist-info/RECORD
